sett_rs-0.7.1.dist-info/METADATA
sett_rs-0.7.1.dist-info/WHEEL
sett_rs/__init__.py
sett_rs/gnupg.py
sett_rs/_sett_rs.pyi
sett_rs/cert.py
sett_rs/py.typed
sett_rs/workflow.py
sett_rs/_sett_rs.cpython-39-darwin.so
sett_rs-0.7.1.dist-info/RECORD
