Metadata-Version: 2.1
Name: sett_rs
Version: 0.7.1
Requires-Dist: ruff ==0.2.2 ; extra == 'dev'
Requires-Dist: mypy ==1.8.0 ; extra == 'dev'
Requires-Dist: pytest ==8.0.2 ; extra == 'dev'
Provides-Extra: dev
Summary: sett-rs Python bindings.
Author: Gerhard Bräunlich <gerhard.braeunlich@id.ethz.ch>, Christian Ribeaud <christian.ribeaud@karakun.com>, Jarosław Surkont <jaroslaw.surkont@unibas.ch>, Simone Guzzi <simone.guzzi@sib.swiss>, Robin Engler <robin.engler@sib.swiss>
Author-email: Gerhard Bräunlich <gerhard.braeunlich@id.ethz.ch>, Christian Ribeaud <christian.ribeaud@karakun.com>, Jarosław Surkont <jaroslaw.surkont@unibas.ch>, Simone Guzzi <simone.guzzi@sib.swiss>, Robin Engler <robin.engler@sib.swiss>
License: LGPL-3.0-or-later
Project-URL: Source Code, https://gitlab.com/biomedit/sett-rs
